pifr-0.1.2.dist-info/METADATA
pifr-0.1.2.dist-info/WHEEL
pifr-0.1.2.dist-info/entry_points.txt
pifr-0.1.2.dist-info/licenses/LICENSE
pifr/__init__.py
pifr/commands/__init__.py
pifr/commands/host.py
pifr/commands/ssh.py
pifr/main.py
pifr-0.1.2.dist-info/RECORD
